NanoPrePro/HTML_report.py
NanoPrePro/__init__.py
NanoPrePro/__main__.py
NanoPrePro/_version.py
NanoPrePro/#optimize/__init__.py
NanoPrePro/#optimize/__main__.py
NanoPrePro/#optimize/argParser.py
NanoPrePro/#optimize/template.py
NanoPrePro/aligntools/__init__.py
NanoPrePro/aligntools/edlibAligner.py
NanoPrePro/paramtools/__init__.py
NanoPrePro/paramtools/argParser.py
NanoPrePro/paramtools/paramsets.py
NanoPrePro/preptools/Annotator.py
NanoPrePro/preptools/Optimizer.py
NanoPrePro/preptools/Processor.py
NanoPrePro/preptools/__init__.py
NanoPrePro/preptools/polyFinder.py
NanoPrePro/seqtools/FastqIO.py
NanoPrePro/seqtools/SeqFastq.py
NanoPrePro/seqtools/__init__.py
nanoprepro-0.0.20.dist-info/licenses/LICENSE
nanoprepro-0.0.20.dist-info/METADATA
nanoprepro-0.0.20.dist-info/WHEEL
nanoprepro-0.0.20.dist-info/entry_points.txt
nanoprepro-0.0.20.dist-info/top_level.txt
nanoprepro-0.0.20.dist-info/RECORD
