Metadata-Version: 2.4
Name: nanoprepro
Version: 0.0.20
Summary: A fully-equipped, fast, and memory-efficient pre-processor for ONT transcriptomic data
Home-page: https://github.com/Woodformation1136/NanoPreP
Author: Chia-Chen Chu
Author-email: b05b01002@ntu.edu.tw
License-File: LICENSE
Requires-Dist: edlib>=1.3.8
Requires-Dist: numpy
Requires-Dist: plotly
Requires-Dist: pandas
Dynamic: author
Dynamic: author-email
Dynamic: description
Dynamic: description-content-type
Dynamic: home-page
Dynamic: license-file
Dynamic: requires-dist
Dynamic: summary
